{
    "Version": "1.2",
    "Data": {
        "Source": "n:\\jams\\moskowjam\\moskowjam\\source\\moskowjam\\moskowjam.cpp",
        "ProvidedModule": "",
        "PCH": "n:\\jams\\moskowjam\\moskowjam\\intermediate\\build\\win64\\x64\\moskowjameditor\\development\\unrealed\\sharedpch.unrealed.project.valapi.cpp20.h.pch",
        "Includes": [
            "n:\\jams\\moskowjam\\moskowjam\\intermediate\\build\\win64\\x64\\unrealeditor\\development\\moskowjam\\definitions.moskowjam.h",
            "n:\\jams\\moskowjam\\moskowjam\\source\\moskowjam\\moskowjam.h"
        ],
        "ImportedModules": [],
        "ImportedHeaderUnits": []
    }
}